propert/__init__.py
propert/autoproperty.py
propert/base.py
propert/classproperty.py
propert/common.py
propert/meta.py
propert/shorthands.py
propert/staticproperty.py
propert/types.py
propert-0.1.4.dist-info/licenses/LICENSE
propert-0.1.4.dist-info/METADATA
propert-0.1.4.dist-info/WHEEL
propert-0.1.4.dist-info/top_level.txt
propert-0.1.4.dist-info/RECORD
