Metadata-Version: 2.4
Name: propert
Version: 0.1.4
Summary: @propert - Static and class-level properties in python
Project-URL: Homepage, https://github.com/maddinkunze/propert
Project-URL: Documentation, https://github.com/maddinkunze/propert/blob/main/README.md
Project-URL: Source, https://github.com/maddinkunze/propert
Requires-Python: >=3.8
License-File: LICENSE
Requires-Dist: typing-extensions
Dynamic: license-file
